[
  {
    "x":0,
    "y":0,
    "w":2,
    "h":2,
    "i":"0",
    "type" : "chart",
    "lineChartData":{
      "datasets":[
        {
          "label":"usl",
          "backgroundColor":"transparent",
          "borderColor":"#ff9948",
          "pointRadius":0,
          "data":[
            30,
            20,
            10
          ]
        }
      ]
    }
  },
  {
    "x":2,
    "y":0,
    "w":2,
    "h":4,
    "i":"1",
    "type" : "chart",
    "lineChartData":{
      "datasets":[
        {
          "label":"usl",
          "backgroundColor":"transparent",
          "borderColor":"#ff9948",
          "pointRadius":0,
          "data":[
            30,
            20,
            10
          ]
        }
      ]
    }
  },
  {
    "x":4,
    "y":0,
    "w":2,
    "h":5,
    "i":"2",
    "type" : "label",
    "text" : "A열"
  },
  {
    "x":6,
    "y":0,
    "w":2,
    "h":3,
    "i":"3",
    "type" : "table",
    "lineChartData":{
      "datasets":[
        {
          "label":"usl",
          "backgroundColor":"transparent",
          "borderColor":"#ff9948",
          "pointRadius":0,
          "data":[
            30,
            20,
            10
          ]
        }
      ]
    }
  },
  {
    "x":8,
    "y":0,
    "w":2,
    "h":3,
    "i":"4",
    "type" : "chart",
    "lineChartData":{
      "datasets":[
        {
          "label":"usl",
          "backgroundColor":"transparent",
          "borderColor":"#ff9948",
          "pointRadius":0,
          "data":[
            30,
            20,
            10
          ]
        }
      ]
    }
  }
]
